{
    "tech_name": "sky130",
    "layer_group_definitions": [
        {
            "name": "li1.Visible",
            "layers": [
                "li1.drawing - 67/20",
                "li1.pin - 67/16",
                "li1.label - 67/5",
                "licon1.drawing - 66/44",
                "mcon.drawing - 67/44"
            ]
        },
        {
            "name": "li1.Selected",
            "layers": [
                "li1.drawing - 67/20"
            ]
        },
        {
            "name": "met1.Visible",
            "layers": [
                "met1.drawing - 68/20",
                "met1.pin - 68/16",
                "met1.label - 68/5",
                "mcon.drawing - 67/44",
                "via.drawing - 68/44"
            ]
        },
        {
            "name": "met1.Selected",
            "layers": [
                "met1.drawing - 68/20"
            ]
        },
        {
            "name": "met2.Visible",
            "layers": [
                "met2.drawing - 69/20",
                "met2.pin - 69/16",
                "met2.label - 69/5",
                "via.drawing - 68/44",
                "via2.drawing - 69/44"
            ]
        },
        {
            "name": "met2.Selected",
            "layers": [
                "met2.drawing - 69/20"
            ]
        },
        {
            "name": "met3.Visible",
            "layers": [
                "met3.drawing - 70/20",
                "met3.pin - 70/16",
                "met3.label - 70/5",
                "via2.drawing - 69/44",
                "via3.drawing - 70/44"
            ]
        },
        {
            "name": "met3.Selected",
            "layers": [
                "met3.drawing - 70/20"
            ]
        },
        {
            "name": "met4.Visible",
            "layers": [
                "met4.drawing - 71/20",
                "met4.pin - 71/16",
                "met4.label - 71/5",
                "via3.drawing - 70/44",
                "via4.drawing - 71/44"
            ]
        },
        {
            "name": "met4.Selected",
            "layers": [
                "met4.drawing - 71/20"
            ]
        },
        {
            "name": "met5.Visible",
            "layers": [
                "met5.drawing - 72/20",
                "met5.pin - 72/16",
                "met5.label - 72/5",
                "via4.drawing - 71/44",
                "pad.drawing - 76/20",
                "pad.pin - 76/16"
            ]
        },
        {
            "name": "met5.Selected",
            "layers": [
                "met5.drawing - 72/20"
            ]
        },
        {
            "name": "poly.Visible",
            "layers": [
                "poly.drawing - 66/20",
                "poly.label - 66/5",
                "poly.pin - 66/16",
                "poly.res - 66/13",
                "licon1.drawing - 66/44",
                "npc.drawing - 95/20"
            ]
        },
        {
            "name": "poly.Selected",
            "layers": [
                "poly.drawing - 66/20"
            ]
        },
        {
            "name": "diff.Visible",
            "layers": [
                "diff.drawing - 65/20",
                "licon1.drawing - 66/44",
                "nwell.drawing - 64/20",
                "dnwell.drawing - 64/18",
                "psdm.drawing - 94/20",
                "nsdm.drawing - 93/44",
                "tap.drawing - 65/44",
                "diff.res - 65/13"
            ]
        },
        {
            "name": "diff.Selected",
            "layers": [
                "diff.drawing - 65/20"
            ]
        }
    ],
    "menu_items": [
        {
            "kind": "shortcut",
            "shortcut": {
                "title": "Show default layers",
                "key": "0",
                "actions": [
                    {
                        "kind": "reset_and_show_all_layers",
                        "layers": {
                            "kind": "all",
                            "layers": null,
                            "layer_groups": null
                        }
                    }
                ]
            }
        },
        {
            "kind": "shortcut",
            "shortcut": {
                "title": "Hide default layers",
                "key": ",",
                "actions": [
                    {
                        "kind": "reset_and_hid_all_layers",
                        "layers": {
                            "kind": "all",
                            "layers": null,
                            "layer_groups": null
                        }
                    }
                ]
            }
        },
        {
            "kind": "separator",
            "shortcut": null
        },
        {
            "kind": "shortcut",
            "shortcut": {
                "title": "Focus on li1 layers",
                "key": "1",
                "actions": [
                    {
                        "kind": "hide_layers",
                        "layers": {
                            "kind": "all",
                            "layers": null,
                            "layer_groups": null
                        }
                    },
                    {
                        "kind": "show_layers",
                        "layers": {
                            "kind": "layer_groups",
                            "layers": null,
                            "layer_groups": [
                                "li1.Visible"
                            ]
                        }
                    },
                    {
                        "kind": "select_layers",
                        "layers": {
                            "kind": "layer_groups",
                            "layers": null,
                            "layer_groups": [
                                "li1.Selected"
                            ]
                        }
                    }
                ]
            }
        },
        {
            "kind": "shortcut",
            "shortcut": {
                "title": "Focus on met1 layers",
                "key": "2",
                "actions": [
                    {
                        "kind": "hide_layers",
                        "layers": {
                            "kind": "all",
                            "layers": null,
                            "layer_groups": null
                        }
                    },
                    {
                        "kind": "show_layers",
                        "layers": {
                            "kind": "layer_groups",
                            "layers": null,
                            "layer_groups": [
                                "met1.Visible"
                            ]
                        }
                    },
                    {
                        "kind": "select_layers",
                        "layers": {
                            "kind": "layer_groups",
                            "layers": null,
                            "layer_groups": [
                                "met1.Selected"
                            ]
                        }
                    }
                ]
            }
        },
        {
            "kind": "shortcut",
            "shortcut": {
                "title": "Focus on met2 layers",
                "key": "3",
                "actions": [
                    {
                        "kind": "hide_layers",
                        "layers": {
                            "kind": "all",
                            "layers": null,
                            "layer_groups": null
                        }
                    },
                    {
                        "kind": "show_layers",
                        "layers": {
                            "kind": "layer_groups",
                            "layers": null,
                            "layer_groups": [
                                "met2.Visible"
                            ]
                        }
                    },
                    {
                        "kind": "select_layers",
                        "layers": {
                            "kind": "layer_groups",
                            "layers": null,
                            "layer_groups": [
                                "met2.Selected"
                            ]
                        }
                    }
                ]
            }
        },
        {
            "kind": "shortcut",
            "shortcut": {
                "title": "Focus on met3 layers",
                "key": "4",
                "actions": [
                    {
                        "kind": "hide_layers",
                        "layers": {
                            "kind": "all",
                            "layers": null,
                            "layer_groups": null
                        }
                    },
                    {
                        "kind": "show_layers",
                        "layers": {
                            "kind": "layer_groups",
                            "layers": null,
                            "layer_groups": [
                                "met3.Visible"
                            ]
                        }
                    },
                    {
                        "kind": "select_layers",
                        "layers": {
                            "kind": "layer_groups",
                            "layers": null,
                            "layer_groups": [
                                "met3.Selected"
                            ]
                        }
                    }
                ]
            }
        },
        {
            "kind": "shortcut",
            "shortcut": {
                "title": "Focus on met4 layers",
                "key": "5",
                "actions": [
                    {
                        "kind": "hide_layers",
                        "layers": {
                            "kind": "all",
                            "layers": null,
                            "layer_groups": null
                        }
                    },
                    {
                        "kind": "show_layers",
                        "layers": {
                            "kind": "layer_groups",
                            "layers": null,
                            "layer_groups": [
                                "met4.Visible"
                            ]
                        }
                    },
                    {
                        "kind": "select_layers",
                        "layers": {
                            "kind": "layer_groups",
                            "layers": null,
                            "layer_groups": [
                                "met4.Selected"
                            ]
                        }
                    }
                ]
            }
        },
        {
            "kind": "shortcut",
            "shortcut": {
                "title": "Focus on met5 layers",
                "key": "6",
                "actions": [
                    {
                        "kind": "hide_layers",
                        "layers": {
                            "kind": "all",
                            "layers": null,
                            "layer_groups": null
                        }
                    },
                    {
                        "kind": "show_layers",
                        "layers": {
                            "kind": "layer_groups",
                            "layers": null,
                            "layer_groups": [
                                "met5.Visible"
                            ]
                        }
                    },
                    {
                        "kind": "select_layers",
                        "layers": {
                            "kind": "layer_groups",
                            "layers": null,
                            "layer_groups": [
                                "met5.Selected"
                            ]
                        }
                    }
                ]
            }
        },
        {
            "kind": "shortcut",
            "shortcut": {
                "title": "Focus on poly layers",
                "key": "8",
                "actions": [
                    {
                        "kind": "hide_layers",
                        "layers": {
                            "kind": "all",
                            "layers": null,
                            "layer_groups": null
                        }
                    },
                    {
                        "kind": "show_layers",
                        "layers": {
                            "kind": "layer_groups",
                            "layers": null,
                            "layer_groups": [
                                "poly.Visible"
                            ]
                        }
                    },
                    {
                        "kind": "select_layers",
                        "layers": {
                            "kind": "layer_groups",
                            "layers": null,
                            "layer_groups": [
                                "poly.Selected"
                            ]
                        }
                    }
                ]
            }
        },
        {
            "kind": "shortcut",
            "shortcut": {
                "title": "Focus on diff layers",
                "key": "9",
                "actions": [
                    {
                        "kind": "hide_layers",
                        "layers": {
                            "kind": "all",
                            "layers": null,
                            "layer_groups": null
                        }
                    },
                    {
                        "kind": "show_layers",
                        "layers": {
                            "kind": "layer_groups",
                            "layers": null,
                            "layer_groups": [
                                "diff.Visible"
                            ]
                        }
                    },
                    {
                        "kind": "select_layers",
                        "layers": {
                            "kind": "layer_groups",
                            "layers": null,
                            "layer_groups": [
                                "diff.Selected"
                            ]
                        }
                    }
                ]
            }
        },
        {
            "kind": "separator",
            "shortcut": null
        },
        {
            "kind": "shortcut",
            "shortcut": {
                "title": "Add li1 layers",
                "key": "Shift+1",
                "actions": [
                    {
                        "kind": "show_layers",
                        "layers": {
                            "kind": "layer_groups",
                            "layers": null,
                            "layer_groups": [
                                "li1.Visible"
                            ]
                        }
                    },
                    {
                        "kind": "select_layers",
                        "layers": {
                            "kind": "layer_groups",
                            "layers": null,
                            "layer_groups": [
                                "li1.Selected"
                            ]
                        }
                    }
                ]
            }
        },
        {
            "kind": "shortcut",
            "shortcut": {
                "title": "Add met1 layers",
                "key": "Shift+2",
                "actions": [
                    {
                        "kind": "show_layers",
                        "layers": {
                            "kind": "layer_groups",
                            "layers": null,
                            "layer_groups": [
                                "met1.Visible"
                            ]
                        }
                    },
                    {
                        "kind": "select_layers",
                        "layers": {
                            "kind": "layer_groups",
                            "layers": null,
                            "layer_groups": [
                                "met1.Selected"
                            ]
                        }
                    }
                ]
            }
        },
        {
            "kind": "shortcut",
            "shortcut": {
                "title": "Add met2 layers",
                "key": "Shift+3",
                "actions": [
                    {
                        "kind": "show_layers",
                        "layers": {
                            "kind": "layer_groups",
                            "layers": null,
                            "layer_groups": [
                                "met2.Visible"
                            ]
                        }
                    },
                    {
                        "kind": "select_layers",
                        "layers": {
                            "kind": "layer_groups",
                            "layers": null,
                            "layer_groups": [
                                "met2.Selected"
                            ]
                        }
                    }
                ]
            }
        },
        {
            "kind": "shortcut",
            "shortcut": {
                "title": "Add met3 layers",
                "key": "Shift+4",
                "actions": [
                    {
                        "kind": "show_layers",
                        "layers": {
                            "kind": "layer_groups",
                            "layers": null,
                            "layer_groups": [
                                "met3.Visible"
                            ]
                        }
                    },
                    {
                        "kind": "select_layers",
                        "layers": {
                            "kind": "layer_groups",
                            "layers": null,
                            "layer_groups": [
                                "met3.Selected"
                            ]
                        }
                    }
                ]
            }
        },
        {
            "kind": "shortcut",
            "shortcut": {
                "title": "Add met4 layers",
                "key": "Shift+5",
                "actions": [
                    {
                        "kind": "show_layers",
                        "layers": {
                            "kind": "layer_groups",
                            "layers": null,
                            "layer_groups": [
                                "met4.Visible"
                            ]
                        }
                    },
                    {
                        "kind": "select_layers",
                        "layers": {
                            "kind": "layer_groups",
                            "layers": null,
                            "layer_groups": [
                                "met4.Selected"
                            ]
                        }
                    }
                ]
            }
        },
        {
            "kind": "shortcut",
            "shortcut": {
                "title": "Add met5 layers",
                "key": "Shift+6",
                "actions": [
                    {
                        "kind": "show_layers",
                        "layers": {
                            "kind": "layer_groups",
                            "layers": null,
                            "layer_groups": [
                                "met5.Visible"
                            ]
                        }
                    },
                    {
                        "kind": "select_layers",
                        "layers": {
                            "kind": "layer_groups",
                            "layers": null,
                            "layer_groups": [
                                "met5.Selected"
                            ]
                        }
                    }
                ]
            }
        },
        {
            "kind": "shortcut",
            "shortcut": {
                "title": "Add poly layers",
                "key": "Shift+8",
                "actions": [
                    {
                        "kind": "show_layers",
                        "layers": {
                            "kind": "layer_groups",
                            "layers": null,
                            "layer_groups": [
                                "poly.Visible"
                            ]
                        }
                    },
                    {
                        "kind": "select_layers",
                        "layers": {
                            "kind": "layer_groups",
                            "layers": null,
                            "layer_groups": [
                                "poly.Selected"
                            ]
                        }
                    }
                ]
            }
        },
        {
            "kind": "shortcut",
            "shortcut": {
                "title": "Add diff layers",
                "key": "Shift+9",
                "actions": [
                    {
                        "kind": "show_layers",
                        "layers": {
                            "kind": "layer_groups",
                            "layers": null,
                            "layer_groups": [
                                "diff.Visible"
                            ]
                        }
                    },
                    {
                        "kind": "select_layers",
                        "layers": {
                            "kind": "layer_groups",
                            "layers": null,
                            "layer_groups": [
                                "diff.Selected"
                            ]
                        }
                    }
                ]
            }
        }
    ]
}
